[{"text": "album", "size": 41.9753086419753}, {"text": "pop", "size": 19.753086419753085}, {"text": "tempo", "size": 17.28395061728395}, {"text": "music", "size": 14.814814814814813}, {"text": "originalfunko", "size": 14.814814814814813}, {"text": "uma", "size": 12.345679012345679}, {"text": "put", "size": 12.345679012345679}, {"text": "rap", "size": 12.345679012345679}, {"text": "life", "size": 9.876543209876543}, {"text": "year", "size": 9.876543209876543}, {"text": "back", "size": 9.876543209876543}, {"text": "pra", "size": 7.4074074074074066}, {"text": "tem", "size": 7.4074074074074066}, {"text": "came", "size": 7.4074074074074066}, {"text": "listening", "size": 7.4074074074074066}, {"text": "com", "size": 7.4074074074074066}, {"text": "wish", "size": 7.4074074074074066}, {"text": "win", "size": 7.4074074074074066}, {"text": "power", "size": 7.4074074074074066}, {"text": "yafavdeyj", "size": 7.4074074074074066}, {"text": "follow", "size": 7.4074074074074066}, {"text": "enjoy", "size": 7.4074074074074066}, {"text": "chance", "size": 7.4074074074074066}, {"text": "k-pop", "size": 7.4074074074074066}, {"text": "thanos", "size": 4.938271604938271}, {"text": "kitap", "size": 4.938271604938271}, {"text": "exo", "size": 4.938271604938271}, {"text": "weareoneexo", "size": 4.938271604938271}, {"text": "fora", "size": 4.938271604938271}, {"text": "quem", "size": 4.938271604938271}, {"text": "writer", "size": 4.938271604938271}, {"text": "bio", "size": 4.938271604938271}, {"text": "jkcorden", "size": 4.938271604938271}, {"text": "exodidthat", "size": 4.938271604938271}, {"text": "boston", "size": 4.938271604938271}, {"text": "person", "size": 4.938271604938271}, {"text": "model", "size": 4.938271604938271}, {"text": "sell", "size": 4.938271604938271}, {"text": "spins", "size": 4.938271604938271}, {"text": "amar", "size": 4.938271604938271}, {"text": "song", "size": 4.938271604938271}, {"text": "mesmo", "size": 4.938271604938271}, {"text": "community", "size": 4.938271604938271}, {"text": "unemployed", "size": 4.938271604938271}, {"text": "vai", "size": 4.938271604938271}, {"text": "como", "size": 4.938271604938271}, {"text": "people", "size": 4.938271604938271}, {"text": "coisas", "size": 4.938271604938271}, {"text": "//t.co/zngvtnrz9s", "size": 4.938271604938271}, {"text": "porra", "size": 4.938271604938271}]